pybtex_docutils/__init__.py
pybtex_docutils/py.typed
pybtex_docutils-1.0.3.dist-info/LICENSE.rst
pybtex_docutils-1.0.3.dist-info/METADATA
pybtex_docutils-1.0.3.dist-info/WHEEL
pybtex_docutils-1.0.3.dist-info/entry_points.txt
pybtex_docutils-1.0.3.dist-info/top_level.txt
pybtex_docutils-1.0.3.dist-info/RECORD
