Metadata-Version: 2.1
Name: pybtex-docutils
Version: 1.0.3
Summary: A docutils backend for pybtex.
Home-page: https://github.com/mcmtroffaes/pybtex-docutils
Download-URL: http://pypi.python.org/pypi/pybtex-docutils
Author: Matthias C. M. Troffaes
Author-email: matthias.troffaes@gmail.com
License: MIT
Platform: any
Classifier: Development Status :: 5 - Production/Stable
Classifier: Environment :: Console
Classifier: Intended Audience :: Developers
Classifier: License :: OSI Approved :: MIT License
Classifier: Operating System :: OS Independent
Classifier: Programming Language :: Python
Classifier: Programming Language :: Python :: 3
Classifier: Programming Language :: Python :: 3.7
Classifier: Programming Language :: Python :: 3.8
Classifier: Programming Language :: Python :: 3.9
Classifier: Programming Language :: Python :: 3.10
Classifier: Programming Language :: Python :: 3.11
Classifier: Topic :: Text Editors :: Text Processing
Classifier: Topic :: Text Processing :: Markup :: XML
Requires-Python: >=3.7
License-File: LICENSE.rst
